langserve/__init__.py
langserve/api_handler.py
langserve/callbacks.py
langserve/chat_playground/.eslintrc.cjs
langserve/chat_playground/.gitignore
langserve/chat_playground/README.md
langserve/chat_playground/dist/assets/index-434ff580.css
langserve/chat_playground/dist/assets/index-86d4d9c0.js
langserve/chat_playground/dist/favicon.ico
langserve/chat_playground/dist/index.html
langserve/chat_playground/index.html
langserve/chat_playground/package.json
langserve/chat_playground/postcss.config.js
langserve/chat_playground/public/favicon.ico
langserve/chat_playground/src/App.css
langserve/chat_playground/src/App.tsx
langserve/chat_playground/src/assets/ArrowUp.svg
langserve/chat_playground/src/assets/ChatIcon.svg
langserve/chat_playground/src/assets/CheckCircleIcon.svg
langserve/chat_playground/src/assets/CheckCircleIcon2.svg
langserve/chat_playground/src/assets/ChevronRight.svg
langserve/chat_playground/src/assets/CircleSpinIcon.svg
langserve/chat_playground/src/assets/CodeIcon.svg
langserve/chat_playground/src/assets/CopyIcon.svg
langserve/chat_playground/src/assets/EmptyState.svg
langserve/chat_playground/src/assets/LangServeLogo.svg
langserve/chat_playground/src/assets/PadlockIcon.svg
langserve/chat_playground/src/assets/PlusIcon.svg
langserve/chat_playground/src/assets/RefreshCW.svg
langserve/chat_playground/src/assets/SendIcon.svg
langserve/chat_playground/src/assets/ShareIcon.svg
langserve/chat_playground/src/assets/ThumbsDownIcon.svg
langserve/chat_playground/src/assets/ThumbsUpIcon.svg
langserve/chat_playground/src/assets/TrashIcon.svg
langserve/chat_playground/src/assets/XCircle.svg
langserve/chat_playground/src/components/AutosizeTextarea.tsx
langserve/chat_playground/src/components/ChatMessage.tsx
langserve/chat_playground/src/components/ChatWindow.tsx
langserve/chat_playground/src/components/ShareDialog.tsx
langserve/chat_playground/src/components/feedback/CorrectnessFeedback.tsx
langserve/chat_playground/src/main.tsx
gigaserve-0.2.3.dist-info/LICENSE
gigaserve-0.2.3.dist-info/METADATA
gigaserve-0.2.3.dist-info/WHEEL
gigaserve-0.2.3.dist-info/RECORD
