Metadata-Version: 2.1
Name: gigaserve
Version: 0.2.3
Summary: 
Home-page: https://github.com/ai-forever/gigaserve
License: LangServe
Author: LangChain
Requires-Python: >=3.8.1,<4.0
Classifier: License :: Other/Proprietary License
Classifier: Programming Language :: Python :: 3
Classifier: Programming Language :: Python :: 3.9
Classifier: Programming Language :: Python :: 3.10
Classifier: Programming Language :: Python :: 3.11
Classifier: Programming Language :: Python :: 3.12
Provides-Extra: all
Provides-Extra: client
Provides-Extra: server
Requires-Dist: fastapi (>=0.90.1,<1) ; extra == "client" or extra == "server" or extra == "all"
Requires-Dist: gigachain-core (>=0.1,<0.3)
Requires-Dist: httpx (>=0.23.0)
Requires-Dist: orjson (>=2)
Requires-Dist: pydantic (>=1)
Requires-Dist: pyproject-toml (>=0.0.10,<0.0.11)
Requires-Dist: sse-starlette (>=1.3.0,<2.0.0) ; extra == "server" or extra == "all"
Project-URL: Repository, https://github.com/ai-forever/gigaserve
